shell_complete/__init__.py
shell_complete/__main__.py
shell_complete/argparse/__init__.py
shell_complete/argparse/action.py
shell_complete/argparse/code.py
shell_complete/argparse/types.py
shell_complete/core/__init__.py
shell_complete/core/_argparse_actions.py
shell_complete/core/generate.py
shell_complete/core/imbued.py
shell_complete/core/writing.py
shell_complete-0.4.2.dist-info/LICENSE
shell_complete-0.4.2.dist-info/METADATA
shell_complete-0.4.2.dist-info/WHEEL
shell_complete-0.4.2.dist-info/entry_points.txt
shell_complete-0.4.2.dist-info/top_level.txt
shell_complete-0.4.2.dist-info/RECORD
